src/fifo.sv
module fifo #(
    parameter DATA_WIDTH = 8,
    parameter FIFO_DEPTH = 8
)(
    input  logic clk,
    input  logic rst,

    input  logic wr_en,
    input  logic rd_en,

    input  logic [DATA_WIDTH-1:0] data_in,
    output logic [DATA_WIDTH-1:0] data_out,

    output logic full,
    output logic empty
);

    localparam ADDR_WIDTH = $clog2(FIFO_DEPTH);

    logic [DATA_WIDTH-1:0] mem [0:FIFO_DEPTH-1];

    logic [ADDR_WIDTH-1:0] wr_ptr;
    logic [ADDR_WIDTH-1:0] rd_ptr;

    logic [ADDR_WIDTH:0] count;

    assign full  = (count == FIFO_DEPTH);
    assign empty = (count == 0);

    always_ff @(posedge clk or posedge rst) begin
        if (rst) begin
            wr_ptr   <= 0;
            rd_ptr   <= 0;
            count    <= 0;
            data_out <= 0;
        end else begin

            // Write into FIFO when write enable is high and FIFO is not full
            if (wr_en && !full) begin
                mem[wr_ptr] <= data_in;
                wr_ptr <= wr_ptr + 1;
            end

            // Read from FIFO when read enable is high and FIFO is not empty
            if (rd_en && !empty) begin
                data_out <= mem[rd_ptr];
                rd_ptr <= rd_ptr + 1;
            end

            // Update number of stored elements
            case ({wr_en && !full, rd_en && !empty})
                2'b10: count <= count + 1;   // only write
                2'b01: count <= count - 1;   // only read
                2'b11: count <= count;       // simultaneous read and write
                default: count <= count;
            endcase

        end
    end

endmodule

tb/fifo_tb.sv
`timescale 1ns/1ps

module fifo_tb;

    logic clk;
    logic rst;

    logic wr_en;
    logic rd_en;

    logic [7:0] data_in;
    logic [7:0] data_out;

    logic full;
    logic empty;

    // Instantiate FIFO
    fifo #(
        .DATA_WIDTH(8),
        .FIFO_DEPTH(8)
    ) dut (
        .clk(clk),
        .rst(rst),
        .wr_en(wr_en),
        .rd_en(rd_en),
        .data_in(data_in),
        .data_out(data_out),
        .full(full),
        .empty(empty)
    );

    // Clock generation: 10 ns clock period
    always #5 clk = ~clk;

    initial begin
        $dumpfile("fifo.vcd");
        $dumpvars(0, fifo_tb);

        clk = 0;
        rst = 1;
        wr_en = 0;
        rd_en = 0;
        data_in = 8'h00;

        // Reset FIFO
        #10;
        rst = 0;

        $display("Starting FIFO Test...");
        $display("---------------------");

        // Write data into FIFO
        write_fifo(8'h11);
        write_fifo(8'h22);
        write_fifo(8'h33);
        write_fifo(8'h44);

        // Read data from FIFO
        read_fifo();
        read_fifo();
        read_fifo();
        read_fifo();

        // Try reading when FIFO is empty
        read_fifo();

        // Fill FIFO completely
        write_fifo(8'hA1);
        write_fifo(8'hA2);
        write_fifo(8'hA3);
        write_fifo(8'hA4);
        write_fifo(8'hA5);
        write_fifo(8'hA6);
        write_fifo(8'hA7);
        write_fifo(8'hA8);

        // Try writing when FIFO is full
        write_fifo(8'hFF);

        // Read all data
        read_fifo();
        read_fifo();
        read_fifo();
        read_fifo();
        read_fifo();
        read_fifo();
        read_fifo();
        read_fifo();

        $display("---------------------");
        $display("FIFO Test Completed.");

        #20;
        $finish;
    end

    task write_fifo(input [7:0] value);
        begin
            @(posedge clk);
            wr_en = 1;
            rd_en = 0;
            data_in = value;

            @(posedge clk);
            wr_en = 0;

            $display("WRITE: data_in = %h | data_out = %h | full = %b | empty = %b",
                     value, data_out, full, empty);
        end
    endtask

    task read_fifo();
        begin
            @(posedge clk);
            wr_en = 0;
            rd_en = 1;

            @(posedge clk);
            rd_en = 0;

            $display("READ : data_out = %h | full = %b | empty = %b",
                     data_out, full, empty);
        end
    endtask

endmodule

fifo.vcd
$date
	Mon Jun 08 11:09:25 2026
$end
$version
	Icarus Verilog
$end
$timescale
	1ps
$end
$scope module fifo_tb $end
$var wire 1 ! full $end
$var wire 1 " empty $end
$var wire 8 # data_out [7:0] $end
$var reg 1 $ clk $end
$var reg 8 % data_in [7:0] $end
$var reg 1 & rd_en $end
$var reg 1 ' rst $end
$var reg 1 ( wr_en $end
$scope module dut $end
$var wire 1 $ clk $end
$var wire 8 ) data_in [7:0] $end
$var wire 1 & rd_en $end
$var wire 1 ' rst $end
$var wire 1 ( wr_en $end
$var wire 1 ! full $end
$var wire 1 " empty $end
$var parameter 32 * ADDR_WIDTH $end
$var parameter 32 + DATA_WIDTH $end
$var parameter 32 , FIFO_DEPTH $end
$var reg 4 - count [3:0] $end
$var reg 8 . data_out [7:0] $end
$var reg 3 / rd_ptr [2:0] $end
$var reg 3 0 wr_ptr [2:0] $end
$upscope $end
$scope task read_fifo $end
$upscope $end
$scope task write_fifo $end
$var reg 8 1 value [7:0] $end
$upscope $end
$upscope $end
$enddefinitions $end
$comment Show the parameter values. $end
$dumpall
b1000 ,
b1000 +
b11 *
$end
#0
$dumpvars
bx 1
b0 0
b0 /
b0 .
b0 -
b0 )
0(
1'
0&
b0 %
0$
b0 #
1"
0!
$end
#5000
1$
#10000
0$
b10001 1
0'
#15000
0"
b1 -
b1 0
b10001 %
b10001 )
1(
1$
#20000
0$
#25000
b100010 1
0(
1$
#30000
0$
#35000
b10 -
b10 0
b100010 %
b100010 )
1(
1$
#40000
0$
#45000
b110011 1
0(
1$
#50000
0$
#55000
b11 -
b11 0
b110011 %
b110011 )
1(
1$
#60000
0$
#65000
b1000100 1
0(
1$
#70000
0$
#75000
b100 -
b100 0
b1000100 %
b1000100 )
1(
1$
#80000
0$
#85000
0(
1$
#90000
0$
#95000
b11 -
b1 /
b10001 #
b10001 .
1&
1$
#100000
0$
#105000
0&
1$
#110000
0$
#115000
b10 -
b10 /
b100010 #
b100010 .
1&
1$
#120000
0$
#125000
0&
1$
#130000
0$
#135000
b1 -
b11 /
b110011 #
b110011 .
1&
1$
#140000
0$
#145000
0&
1$
#150000
0$
#155000
1"
b0 -
b100 /
b1000100 #
b1000100 .
1&
1$
#160000
0$
#165000
0&
1$
#170000
0$
#175000
1&
1$
#180000
0$
#185000
b10100001 1
0&
1$
#190000
0$
#195000
0"
b1 -
b101 0
b10100001 %
b10100001 )
1(
1$
#200000
0$
#205000
b10100010 1
0(
1$
#210000
0$
#215000
b10 -
b110 0
b10100010 %
b10100010 )
1(
1$
#220000
0$
#225000
b10100011 1
0(
1$
#230000
0$
#235000
b11 -
b111 0
b10100011 %
b10100011 )
1(
1$
#240000
0$
#245000
b10100100 1
0(
1$
#250000
0$
#255000
b100 -
b0 0
b10100100 %
b10100100 )
1(
1$
#260000
0$
#265000
b10100101 1
0(
1$
#270000
0$
#275000
b101 -
b1 0
b10100101 %
b10100101 )
1(
1$
#280000
0$
#285000
b10100110 1
0(
1$
#290000
0$
#295000
b110 -
b10 0
b10100110 %
b10100110 )
1(
1$
#300000
0$
#305000
b10100111 1
0(
1$
#310000
0$
#315000
b111 -
b11 0
b10100111 %
b10100111 )
1(
1$
#320000
0$
#325000
b10101000 1
0(
1$
#330000
0$
#335000
1!
b1000 -
b100 0
b10101000 %
b10101000 )
1(
1$
#340000
0$
#345000
b11111111 1
0(
1$
#350000
0$
#355000
b11111111 %
b11111111 )
1(
1$
#360000
0$
#365000
0(
1$
#370000
0$
#375000
0!
b111 -
b101 /
b10100001 #
b10100001 .
1&
1$
#380000
0$
#385000
0&
1$
#390000
0$
#395000
b110 -
b110 /
b10100010 #
b10100010 .
1&
1$
#400000
0$
#405000
0&
1$
#410000
0$
#415000
b101 -
b111 /
b10100011 #
b10100011 .
1&
1$
#420000
0$
#425000
0&
1$
#430000
0$
#435000
b100 -
b0 /
b10100100 #
b10100100 .
1&
1$
#440000
0$
#445000
0&
1$
#450000
0$
#455000
b11 -
b1 /
b10100101 #
b10100101 .
1&
1$
#460000
0$
#465000
0&
1$
#470000
0$
#475000
b10 -
b10 /
b10100110 #
b10100110 .
1&
1$
#480000
0$
#485000
0&
1$
#490000
0$
#495000
b1 -
b11 /
b10100111 #
b10100111 .
1&
1$
#500000
0$
#505000
0&
1$
#510000
0$
#515000
1"
b0 -
b100 /
b10101000 #
b10101000 .
1&
1$
#520000
0$
#525000
0&
1$
